cloudstorage/__init__.py
cloudstorage/api_utils.py
cloudstorage/cloudstorage_api.py
cloudstorage/common.py
cloudstorage/errors.py
cloudstorage/rest_api.py
cloudstorage/storage_api.py
cloudstorage/test_utils.py
cloudstorage/port/__init__.py
cloudstorage/port/cloudstorage_stub.py
cloudstorage/port/stub_dispatcher.py
cloudstorage/port/testbed.py
GoogleAppEngineCloudStorageClientPy3-3.0.0.dist-info/LICENSE
GoogleAppEngineCloudStorageClientPy3-3.0.0.dist-info/METADATA
GoogleAppEngineCloudStorageClientPy3-3.0.0.dist-info/WHEEL
GoogleAppEngineCloudStorageClientPy3-3.0.0.dist-info/top_level.txt
GoogleAppEngineCloudStorageClientPy3-3.0.0.dist-info/RECORD
