Metadata-Version: 2.1
Name: GoogleAppEngineCloudStorageClientPy3
Version: 3.0.0
Summary: This library is the preferred way of accessing Google
Author-email: Kamil Turek <kamil.turek@hotmail.com>
License: Apache-2.0
Keywords: google,app engine,cloud storage
Classifier: Intended Audience :: Developers
Classifier: License :: OSI Approved :: Apache Software License
Classifier: Programming Language :: Python
Classifier: Programming Language :: Python :: 3
Classifier: Programming Language :: Python :: 3.7
Classifier: Programming Language :: Python :: 3.8
Classifier: Programming Language :: Python :: 3.9
Classifier: Programming Language :: Python :: 3.10
Classifier: Programming Language :: Python :: 3.11
Classifier: Operating System :: OS Independent
Classifier: Topic :: Internet
Requires-Python: >=3.7
License-File: LICENSE
Requires-Dist: appengine-python-standard
